cs/ebooks/__init__.py
cs/ebooks/__main__.py
cs/ebooks/apple.py
cs/ebooks/calibre.py
cs/ebooks/cbz.py
cs/ebooks/common.py
cs/ebooks/dedrm.py
cs/ebooks/kobo.py
cs/ebooks/mobi.py
cs/ebooks/pdf.py
cs.ebooks-20241007.dist-info/METADATA
cs.ebooks-20241007.dist-info/WHEEL
cs.ebooks-20241007.dist-info/entry_points.txt
cs.ebooks-20241007.dist-info/top_level.txt
cs.ebooks-20241007.dist-info/RECORD
