Metadata-Version: 2.1
Name: cs.ebooks
Version: 20241007
Summary: Utilities and command line for working with EBooks. Basic support for talking to Apple Books, Calibre, CBZ, Kindle, Kobo, Mobi, PDF. These form the basis of my personal Kindle/Kobo/Calibre workflow.
Author-email: Cameron Simpson <cs@cskk.id.au>
License: GNU General Public License v3 or later (GPLv3+)
Project-URL: Monorepo Hg/Mercurial Mirror, https://hg.sr.ht/~cameron-simpson/css
Project-URL: Monorepo Git Mirror, https://github.com/cameron-simpson/css
Project-URL: MonoRepo Commits, https://bitbucket.org/cameron_simpson/css/commits/branch/main
Project-URL: Source, https://github.com/cameron-simpson/css/blob/main/lib/python/cs/ebooks
Keywords: python3
Classifier: Programming Language :: Python
Classifier: Programming Language :: Python :: 3
Classifier: Development Status :: 4 - Beta
Classifier: Intended Audience :: Developers
Classifier: Operating System :: OS Independent
Classifier: Topic :: Software Development :: Libraries :: Python Modules
Classifier: License :: OSI Approved :: GNU General Public License v3 or later (GPLv3+)
Requires-Dist: cs.app.osx.defaults >=20240316
Requires-Dist: cs.app.osx.plist >=20221228
Requires-Dist: cs.binary >=20240630
Requires-Dist: cs.buffer >=20240630
Requires-Dist: cs.cmdutils >=20241007
Requires-Dist: cs.context >=20240630
Requires-Dist: cs.debug >=20241005
Requires-Dist: cs.deco >=20241007
Requires-Dist: cs.fileutils >=20241007.1
Requires-Dist: cs.fs >=20241007
Requires-Dist: cs.fstags >=20241005
Requires-Dist: cs.gimmicks >=20240316
Requires-Dist: cs.lex >=20240630
Requires-Dist: cs.logutils >=20241007
Requires-Dist: cs.numeric >=20220606
Requires-Dist: cs.obj >=20241005
Requires-Dist: cs.pfx >=20240630
Requires-Dist: cs.progress >=20240412
Requires-Dist: cs.psutils >=20240316
Requires-Dist: cs.queues >=20240412
Requires-Dist: cs.resources >=20241005
Requires-Dist: cs.sqlalchemy-utils >=20241005
Requires-Dist: cs.sqltags >=20240723
Requires-Dist: cs.tagset >=20241007
Requires-Dist: cs.threads >=20241005
Requires-Dist: cs.units
Requires-Dist: cs.upd >=20240630
Requires-Dist: cs.x >=20240630
Requires-Dist: icontract
Requires-Dist: mobi
Requires-Dist: pillow
Requires-Dist: pycryptodomex
Requires-Dist: sqlalchemy
Requires-Dist: typeguard
